newsfeedback/__init__.py
newsfeedback/defaults/default_homepage_config.yaml
newsfeedback/defaults/default_metadata_config.yaml
newsfeedback/main.py
newsfeedback-0.1.0.dist-info/entry_points.txt
newsfeedback-0.1.0.dist-info/LICENSE
newsfeedback-0.1.0.dist-info/METADATA
newsfeedback-0.1.0.dist-info/WHEEL
newsfeedback-0.1.0.dist-info/RECORD
