Metadata-Version: 2.1
Name: newsfeedback
Version: 0.1.0
Summary: Tool for extracting and saving news article metadata at regular intervals.
License: MIT
Author: Rahel Winter and Felix Victor Münch
Requires-Python: >=3.8,<4.0
Classifier: License :: OSI Approved :: MIT License
Classifier: Programming Language :: Python :: 3
Classifier: Programming Language :: Python :: 3.8
Classifier: Programming Language :: Python :: 3.9
Classifier: Programming Language :: Python :: 3.10
Classifier: Programming Language :: Python :: 3.11
Requires-Dist: PyYAML
Requires-Dist: bs4 (>=0.0.1,<0.0.2)
Requires-Dist: click
Requires-Dist: loguru
Requires-Dist: pandas (>=1.5.3,<2.0.0)
Requires-Dist: pytest-html (>=3.2.0,<4.0.0)
Requires-Dist: schedule (>=1.1.0,<2.0.0)
Requires-Dist: selenium (>=4.8.0,<5.0.0)
Requires-Dist: trafilatura (>=1.4.1,<2.0.0)
Requires-Dist: webdriver-manager (>=3.8.5,<4.0.0)
